{
  "format": {
    "Background": {
      "shift": 0,
      "mask": "0x1f",
      "bits": 5
    },
    "Facility": {
      "shift": 5,
      "mask": "0x1f",
      "bits": 5
    },
    "Body": {
      "shift": 10,
      "mask": "0x3",
      "bits": 2
    },
    "Clothes": {
      "shift": 12,
      "mask": "0xf",
      "bits": 4
    },
    "Eyes": {
      "shift": 16,
      "mask": "0xf",
      "bits": 4
    },
    "Head": {
      "shift": 20,
      "mask": "0xf",
      "bits": 4
    }
  },
  "indices": {
    "Background": [
      "Strata Flux",
      "Strata Reactor",
      "Strata Veins",
      "Strata Ignite",
      "Strata Pulse",
      "Strata Fusion",
      "Catalisys Cascade",
      "Catalisys Core",
      "Catalisys Distill",
      "Catalisys Circuit",
      "Octanergy Surge",
      "Octanergy Blaze",
      "Octanergy Voltage",
      "Nucleus Azure",
      "Nucleus Radiance",
      "Nucleus Ember",
      "Nucleus Inferno",
      "Pixel-Oyl",
      "Oyl",
      "Hyperfuel"
    ],
    "Facility": [
      "none",
      "Oyl Tower",
      "Burning Tower",
      "Leaking Tower",
      "Factory",
      "Main Lab",
      "Chemical Lab",
      "Mini Lab",
      "Distillation Lab",
      "Containers",
      "Radioactive",
      "Pipes",
      "Butane",
      "Fartane",
      "Methane",
      "Diesel",
      "Airhead"
    ],
    "Body": [
      "Dead",
      "Burnt",
      "Oyl Alkalution",
      "Acid Alkalution"
    ],
    "Clothes": [
      "none",
      "Tank Top Black",
      "Tank Top White",
      "Jacket",
      "Alkanes Jacket",
      "Holey Jacket",
      "Protective Jacket",
      "White Hoodie",
      "Black Hoodie",
      "Gradient Hoodie",
      "Construction Overalls",
      "Chemical Protective Suit",
      "Chemical Protective Suit Hooded",
      "Protective Suit"
    ],
    "Eyes": [
      "Empty",
      "Blue",
      "Orange",
      "Mysterious",
      "Oyl Heterochromia",
      "Acid Heterochromia",
      "Boss",
      "Safety Glasses",
      "Futuristic Glasses",
      "Visor"
    ],
    "Head": [
      "none",
      "Helmet Blue",
      "Helmet Orange",
      "Destruction",
      "Respirator Orange",
      "Respirator Blue",
      "Chemists Respirator",
      "Cigarette",
      "Boss"
    ]
  },
  "items": [
    1123378,
    5308518,
    110798,
    3410304,
    5259392,
    18892,
    462894,
    1323012,
    3174473,
    218501,
    2621678,
    2229349,
    1252398,
    3344836,
    3473481,
    2691184,
    4460709,
    3416416,
    1051877,
    2163850,
    1253425,
    2102312,
    2114607,
    217585,
    7479368,
    1515716,
    74758,
    1311852,
    606370,
    3616782,
    2228263,
    1204705,
    6300107,
    135494,
    135269,
    2294056,
    69704,
    1253387,
    77902,
    557074,
    177350,
    3448971,
    6750339,
    49454,
    2556971,
    2240712,
    4616640,
    3354976,
    3244385,
    65536,
    3289377,
    3223751,
    1216515,
    3343488,
    2113603,
    2322755,
    237857,
    6500641,
    4534634,
    3282144,
    278984,
    286794,
    3314720,
    4404522,
    1163584,
    3309578,
    1581100,
    6488109,
    5579178,
    3220518,
    143629,
    2199566,
    3236067,
    2165866,
    7942184,
    6795365,
    1312038,
    69958,
    307235,
    29038,
    6374824,
    2306281,
    2249777,
    2199937,
    4419631,
    4211108,
    3362820,
    1180006,
    5250372,
    1316907,
    2204704,
    1249550,
    3290212,
    4260004,
    3227847,
    1528001,
    2237729,
    20589,
    3462376,
    3671534,
    3559436,
    1122566,
    1225068,
    3539393,
    4524114,
    3211692,
    78032,
    1450026,
    4740523,
    5718191,
    1537318,
    3539012,
    5357664,
    3293517,
    1466659,
    1310862,
    6500550,
    7689543,
    4407305,
    5714025,
    7610668,
    3297485,
    402576,
    4616387,
    2183522,
    6489350,
    1200291,
    37195,
    6824134,
    414126,
    2113546,
    3301481,
    1249537,
    4615338,
    1230026,
    504224,
    2310316,
    2166953,
    114884,
    1191368,
    3297284,
    4264198,
    66725,
    8753673,
    3751936,
    6632458,
    5309537,
    133442,
    5399753,
    1422572,
    3285029,
    12449,
    8552645,
    3145889,
    426029,
    8520192,
    1134697,
    3604492,
    5644293,
    3363305,
    3674225,
    6385864,
    1441923,
    3408176,
    3490890,
    38051,
    160102,
    139777,
    6311150,
    35,
    3342724,
    5505281,
    3290337,
    4204619,
    4272229,
    205925,
    458,
    3723301,
    6443141,
    1052865,
    4334626,
    2638181,
    2230562,
    4210691,
    526371,
    1127562,
    143754,
    5574892,
    426414,
    2228324,
    5242988,
    4434129,
    4654405,
    1185232,
    5378178,
    5420520,
    4396364,
    4731203,
    4329609,
    4342157,
    5341216,
    139312,
    2174983,
    5508297,
    6557709,
    4325633,
    4202784,
    3289284,
    2101603,
    2130276,
    8668354,
    483560,
    2100495,
    4464961,
    5484736,
    1056165,
    2163982,
    3434721,
    282802,
    1056939,
    2248842,
    1409159,
    2327938,
    5710060,
    335907,
    409612,
    3214533,
    7426055,
    201185,
    3215366,
    2362671,
    1026,
    5583113,
    7483563,
    3487109,
    1577026,
    8597921,
    6653102,
    2109890,
    2236450,
    4200682,
    5548483,
    86275,
    1050698,
    3426410,
    365005,
    2498593,
    4497700,
    213262,
    2175367,
    8458368,
    1280032,
    4600199,
    7602466,
    3434673,
    7382253,
    73936,
    5326926,
    5288167,
    2136521,
    3546280,
    6381575,
    3277061,
    3612785,
    4219023,
    6566320,
    6305064,
    3211493,
    1388584,
    1065383,
    4334950,
    5522564,
    5394606,
    4600037,
    5534056,
    2115904,
    475153,
    3219823,
    12363,
    4666792,
    1593606,
    3605770,
    3342666,
    3276864,
    4341897,
    3343429,
    5259536,
    1213474,
    4285506,
    3543207,
    2175146,
    1312071,
    337120,
    3215823,
    6632464,
    7958536,
    3289446,
    3551665,
    562535,
    8851715,
    5242948,
    2326756,
    3257348,
    229614,
    3444804,
    3650599,
    1191943,
    3154025,
    6492385,
    6817956,
    1085810,
    1200271,
    2211845,
    1219659,
    1179879,
    5378503,
    4346277,
    427329,
    2298250,
    4600005,
    2179168,
    282693,
    4613570,
    1249388,
    5320928,
    7348229,
    2269381,
    159939,
    132263,
    1392940,
    1261761,
    4677700,
    3371235,
    4478020,
    24590,
    3346474,
    541027,
    2203783,
    5506149,
    3346702,
    344425,
    465988,
    181613,
    169350,
    3154155,
    5314949,
    3671392,
    3547376,
    307331,
    36928,
    3145743,
    2134186,
    2142412,
    1204615,
    1387694,
    8544,
    6309152,
    3348974,
    2205196,
    278668,
    3559720,
    2641089,
    2429127,
    274631,
    5710989,
    6698285,
    2429120,
    475362,
    1291497,
    2576623,
    1155332,
    545120,
    5388657,
    3281128,
    65611,
    4330984,
    2241606,
    6316399,
    222217,
    2298061,
    1074341,
    3612906,
    3543498,
    3375118,
    5353572,
    1204321,
    3342466,
    3158321,
    2314512,
    5505060,
    7561254,
    492645,
    4604292,
    1114510,
    1142986,
    3452230,
    5390668,
    6764944,
    1260773,
    1115203,
    1446,
    2281696,
    2629932,
    6557995,
    1452105,
    4595713,
    4297730,
    3174594,
    1597671,
    3485004,
    33004,
    77857,
    1249574,
    1548431,
    2294061,
    1229924,
    3392651,
    5382347,
    6697132,
    3379331,
    4346063,
    398662,
    4280517,
    1380612,
    364618,
    1053035,
    9520,
    2498602,
    20839,
    78118,
    4612130,
    3186824,
    4244513,
    1265697,
    2463909,
    3151184,
    5252264,
    3166320,
    3477634,
    106993,
    3539275,
    373190,
    241769,
    7434498,
    4542470,
    5702818,
    4436256,
    4284524,
    5309699,
    1229871,
    6562144,
    6511746,
    4657421,
    2253221,
    2326834,
    4415493,
    5472583,
    1148034,
    2298214,
    1348737,
    197777,
    69761,
    5510148,
    27941,
    3289088,
    1052896,
    1066436,
    7413871,
    1123729,
    4219151,
    3310790,
    3261740,
    2240714,
    2580674,
    3414056,
    5857446,
    2557006,
    2437123,
    472399,
    7561234,
    393616,
    1446059,
    7606347,
    101446,
    3345644,
    4538688,
    3623974,
    106668,
    462860,
    1201442,
    471140,
    6301927,
    1425446,
    4243599,
    2543877,
    4215145,
    1384709,
    4282471,
    1085609,
    3342626,
    1311078,
    470215,
    1442054,
    4260173,
    2248968,
    5384391,
    2441514,
    5268931,
    4206956,
    4525131,
    1114124,
    5330030,
    2498630,
    1272139,
    6455648,
    6620295,
    524587,
    3146944,
    3584240,
    2129952,
    5571810,
    2429225,
    1196098,
    1257831,
    2371757,
    280613,
    2514977,
    348584,
    213419,
    1148160,
    5312970,
    242062,
    6303946,
    73735,
    1118688,
    12296,
    197929,
    3515627,
    593920,
    1573195,
    6299913,
    1320999,
    1081731,
    4591628,
    4403663,
    263206,
    4395360,
    1081737,
    286857,
    6324227,
    4587748,
    135499,
    4743626,
    409609,
    3310059,
    6306818,
    1450189,
    1257604,
    5260749,
    1285450,
    5243018,
    441472,
    2625797,
    2239488,
    2233446,
    286914,
    2105709,
    2232768,
    332004,
    459953,
    2568514,
    2460972,
    8294,
    135557,
    1523909,
    4337993,
    3250634,
    1515596,
    6357133,
    4493603,
    77989,
    5457132,
    548910,
    6410316,
    143520,
    6554720,
    2344161,
    5308870,
    1442963,
    2708901,
    131242,
    4424037,
    1288492,
    1520010,
    6619527,
    3371430,
    532835,
    3576262,
    7418176,
    5779620,
    2109473,
    94466,
    4481418,
    3371367,
    4337804,
    6410304,
    435556,
    7353547,
    2163952,
    2232846,
    5719136,
    5505284,
    5456203,
    398664,
    1121634,
    2507206,
    4587823,
    467075,
    94402,
    4392110,
    336010,
    218383,
    1118240,
    3421486,
    4203585,
    426178,
    1066000,
    2273709,
    162977,
    364773,
    430281,
    1118211,
    2338816,
    1117360,
    1257696,
    5452033,
    3380465,
    1053936,
    151590,
    4206666,
    1245617,
    294922,
    1249664,
    1219648,
    1073608,
    2330891,
    1402379,
    135432,
    336129,
    6586479,
    3158254,
    4456491,
    1216911,
    1117417,
    1189265,
    5742723,
    1291407,
    1188102,
    5836832,
    197870,
    2105858,
    274564,
    1405197,
    1487240,
    3170406,
    2566441,
    6380801,
    222278,
    1056879,
    231689,
    1082377,
    41226,
    196864,
    148740,
    3511523,
    77830,
    1471812,
    2510867,
    573486,
    3145994,
    147499,
    274507,
    155840,
    3167329,
    2388224,
    404704,
    6669350,
    327880,
    4464933,
    1204361,
    3485804,
    3295749,
    8871950,
    5374147,
    65668,
    1164320,
    151559,
    5447690,
    2344139,
    5383180,
    160136,
    193,
    82240,
    1638511,
    1146880,
    1548294,
    2322693,
    2432111,
    3158122,
    5378082,
    4204875,
    1140745,
    4206981,
    5509570,
    7680074,
    6361347,
    1179789,
    1450183,
    3280942,
    3482660,
    6888835,
    458823,
    4731405,
    7602216,
    1129542,
    153765,
    4220010,
    86319,
    1134856,
    4358308,
    5583110,
    6620263,
    68806,
    5391458,
    6313154,
    4612356,
    3285105,
    143790,
    8654892,
    8655113,
    3293347,
    4489258,
    1343528,
    3740771,
    3432840,
    3298440,
    4392333,
    5251106,
    3282080,
    69793,
    475297,
    5308581,
    2102277,
    8802405,
    348361,
    491845,
    5477393,
    2506989,
    1192231,
    6501411,
    24645,
    1187873,
    1355840,
    24773,
    7414819,
    3228684,
    1526955,
    3424296,
    6497736,
    1423495,
    1257669,
    5382668,
    4239622,
    4398476,
    4362336,
    45281,
    3290338,
    544867,
    2166822,
    8561091,
    205088,
    1246247,
    3411205,
    1464708,
    143650,
    2237510,
    1124482,
    5325034,
    3514530,
    4329475,
    6500779,
    5244970,
    239859,
    1380646,
    1265899,
    241766,
    2302179,
    3383588,
    3153955,
    2202754,
    2445669,
    3241408,
    2453665,
    5701728,
    8912911,
    5386470,
    2437421,
    1314053,
    2371820,
    3233000,
    4538512,
    3145934,
    2105664,
    4287952,
    5656871,
    151694,
    3481761,
    3150050,
    5595470,
    1343879,
    4331552,
    6513826,
    3222882,
    1130508,
    205155,
    86317,
    1327235,
    7377088,
    2367593,
    6423913,
    3375180,
    205003,
    152972,
    221385,
    131376,
    2121869,
    6291744,
    2560362,
    2293891,
    1409423,
    5308749,
    5574921,
    4260874,
    5398885,
    4800610,
    5448019,
    3162216,
    4485131,
    1524194,
    3498307,
    2142220,
    2381129,
    2310318,
    1261806,
    3674466,
    2163109,
    335147,
    3228677,
    3347617,
    2314438,
    2371850,
    4522272,
    3317897,
    1253548,
    4755755,
    378124,
    4489472,
    1200194,
    6320300,
    5469283,
    3227783,
    2261152,
    4215108,
    6357231,
    2370922,
    8192,
    2097669,
    4265217,
    2383916,
    5460170,
    213091,
    8400910,
    1142797,
    5575763,
    2438217,
    2298186,
    3158145,
    2363691,
    4473059,
    3162436,
    2164749,
    6709249,
    1188962,
    6620418,
    1458471,
    148747,
    3756328,
    6373413,
    8728800,
    3538988,
    3256324,
    2372650,
    2122112,
    1085869,
    1057088,
    2473991,
    1216520,
    2113769,
    5709832,
    4366824,
    6431143,
    1048879,
    2228751,
    2162790,
    209230,
    1196295,
    3282245,
    422187,
    92612,
    3473446,
    5701858,
    2310433,
    3223850,
    7344385,
    24578,
    4653256,
    2277386,
    2441380,
    3473674,
    1052672,
    3621121,
    2102401,
    395367,
    3490831,
    3277006,
    3220678,
    2245730,
    5385707,
    2162726,
    5282126,
    173313,
    4311464,
    2527310,
    6365583,
    3510759,
    2445641,
    5251393,
    2581770,
    4198695,
    6307151,
    3604679,
    4210987,
    4472833,
    4268261,
    243017,
    65968,
    86050,
    4194411,
    3376620,
    4358354,
    4210828,
    4395328,
    6488068,
    4728067,
    7574695,
    26023,
    3191105,
    634944,
    15552,
    4345006,
    6562053,
    6578218,
    277735,
    7762285,
    3318023,
    6444164,
    7476561,
    6828035,
    3187020,
    6422794,
    405773,
    2204869,
    8302,
    3358797,
    5681191,
    6361299,
    4342281,
    143439,
    4460876,
    4657441,
    7868576,
    5251340,
    1265739,
    2297891,
    5318671,
    4329644,
    3227696,
    2302307,
    6340812,
    2277647,
    3289568,
    1197389,
    107,
    1324394,
    2257263,
    6341702,
    1450371,
    4391113,
    3425288,
    3276800,
    1376270,
    3574223,
    1180705,
    3293357,
    4423820,
    4206,
    1114131,
    2101452,
    312644,
    5271691,
    4416521,
    1058881,
    186593,
    77960,
    1187916,
    2098338,
    4796584,
    2378948,
    2183625,
    1220942,
    3150855,
    6656198,
    2507055,
    1319371,
    2252874,
    7348324,
    6423722,
    3437572,
    28832,
    5130,
    6463776,
    2367494,
    401729,
    99340,
    5279881,
    7364806,
    155776,
    340291,
    3148810,
    69667,
    2384015,
    2327842,
    499886,
    6365282,
    1061105,
    364614,
    1127749,
    478406,
    4805064,
    2261481,
    72709,
    3519496,
    404777,
    3150913,
    1056804,
    2314347,
    3176777,
    399788,
    6865163,
    6357032,
    1384908,
    3150338,
    6345166,
    5585131,
    6292717,
    2568487,
    70669,
    1587653,
    565711,
    221648,
    1058218,
    2425131,
    3212684,
    1663072,
    263618,
    225444,
    3485698,
    2277516,
    1114349,
    278532,
    7495686,
    1401071,
    6701282,
    8197,
    5457035,
    4485472,
    3218436,
    8537423,
    2175438,
    2174125,
    5312647,
    4211920,
    4227174,
    8831399,
    2252941,
    98571,
    4303049,
    5681410,
    5275888,
    29031,
    2257260,
    2245089,
    4467008,
    1058055,
    5888199,
    3280939,
    3518702,
    1089647,
    4394057,
    2330754,
    6304074,
    4267055,
    3276992,
    3408098,
    5309601,
    5472263,
    110692,
    2097186,
    7496706,
    4736098,
    1526022,
    1262055,
    3223659,
    3285026,
    5517602,
    1385672,
    1205443,
    6362635,
    4194466,
    4272274,
    69898,
    2121967,
    6357102,
    1163399,
    1350848,
    1208530,
    1065261,
    5292044,
    94273,
    99721,
    1131657,
    6332552,
    1192396,
    6300111,
    201070,
    5505194,
    8540416,
    5588205,
    262315,
    6406278,
    173546,
    2371587,
    336079,
    1246375,
    1394824,
    102631,
    3158306,
    2232521,
    6643754,
    2316388,
    2441488,
    4368689,
    3289355,
    2129958,
    2183626,
    4479212,
    2122886,
    6431179,
    3178882,
    4350345,
    6496362,
    20801,
    393262,
    2126213,
    6303753,
    149762,
    4283398,
    1441830,
    8478792,
    1209568,
    4396393,
    146595,
    3281323,
    4194561,
    5398888,
    32867,
    5477632,
    4588769,
    3256322,
    4210949,
    4527329,
    1212649,
    2117838,
    169132,
    411111,
    3228073,
    2130016,
    7472589,
    8396942,
    2294029,
    4352129,
    278628,
    5318056,
    1191944,
    1450094,
    364,
    1114250,
    98343,
    3768556,
    3440744,
    134597,
    74025,
    2568321,
    5588112,
    28975,
    1265761,
    2404544,
    357444,
    405766,
    1245449,
    545025,
    7445572,
    2449705,
    1508582,
    5449154,
    151657,
    2408966,
    1188268,
    8794280,
    5640225,
    4673826,
    1048737,
    5335375,
    5587110,
    4399370,
    1114156,
    78059,
    3223684,
    5656707,
    5390571,
    1116200,
    1155105,
    2433057,
    2597062,
    2301965,
    1081583,
    405513,
    4469955,
    135330,
    2461842,
    4268035,
    196934,
    6292654,
    2571312,
    2131171,
    5263717,
    8770024,
    2121860,
    459240,
    3166374,
    1589388,
    5714019,
    5709901,
    2360484,
    69800,
    5251469,
    66597,
    3287213,
    6291783,
    3368192,
    1052903,
    1100804,
    1562789,
    2113710,
    5743756,
    1269888,
    7496004,
    4399203,
    3245216,
    33899,
    2363690,
    1266880,
    94242,
    1130511,
    4194401,
    2097267,
    205835,
    4264046,
    336995,
    2184655
  ]
}